pyaskit/__init__.py
pyaskit/code_generator.py
pyaskit/config.py
pyaskit/decorator.py
pyaskit/dialog.py
pyaskit/example.py
pyaskit/function.py
pyaskit/function_name.py
pyaskit/llm.py
pyaskit/llm_claude.py
pyaskit/llm_cohere.py
pyaskit/llm_gemini.py
pyaskit/llm_llama.py
pyaskit/llm_openai.py
pyaskit/logging_config.py
pyaskit/models.py
pyaskit/path.py
pyaskit/prompt.py
pyaskit/py_askit.py
pyaskit/template.py
pyaskit/types/__init__.py
pyaskit/types/converter.py
pyaskit/types/schema.py
pyaskit/types/type_printer.py
pyaskit/types/types.py
pyaskit-1.4.6.dist-info/LICENSE
pyaskit-1.4.6.dist-info/METADATA
pyaskit-1.4.6.dist-info/WHEEL
pyaskit-1.4.6.dist-info/top_level.txt
pyaskit-1.4.6.dist-info/RECORD
