Metadata-Version: 2.1
Name: pyaskit
Version: 1.4.6
Summary: AskIt: Unified programming interface for programming with large language models (GPT-3.5, GPT-4, Gemini, Claude, COHERE, Llama 2)
Home-page: https://github.com/katsumiok/pyaskit
Author: Katsumi Okuda
Author-email: okuda@csail.mit.edu
License: MIT
Keywords: openai,gpt,gpt-3,gpt-4,google,gemini,claude,cohere,llama,api,wrapper,framework,dsl,llm
Platform: UNKNOWN
Classifier: Programming Language :: Python
Classifier: Topic :: Scientific/Engineering :: Artificial Intelligence
Classifier: License :: OSI Approved :: MIT License
Requires-Python: >=3.8
Requires-Dist: openai>=1.12.0
Requires-Dist: unidecode
Requires-Dist: timeout-decorator
Requires-Dist: astor
Requires-Dist: typing-extensions
